dv_mock_api/__init__.py
dv_mock_api/enums.py
dv_mock_api/main.py
dv_mock_api/runner.py
dv_mock_api/settings.py
dv_mock_api/helpers/__init__.py
dv_mock_api/helpers/prefilter.py
dv_mock_api/models/__init__.py
dv_mock_api/models/advertiser.py
dv_mock_api/models/dbm_request.py
dv_mock_api/models/dv_request.py
dv_mock_api/models/lineitem.py
dv_mock_api/models/partner.py
dv_mock_api/models/report.py
dv_mock_api/reports/__init__.py
dv_mock_api/reports/billable_outcome.csv
dv_mock_api/reports/empty.csv
dv_mock_api/reports/platform_fee.csv
dv_mock_api/reports/spend.csv
dv_mock_api/routes/__init__.py
dv_mock_api/routes/advertiser.py
dv_mock_api/routes/discovery.py
dv_mock_api/routes/lineitem.py
dv_mock_api/routes/partner.py
dv_mock_api/routes/reporting.py
dv_mock_api-0.1.2.dist-info/METADATA
dv_mock_api-0.1.2.dist-info/WHEEL
dv_mock_api-0.1.2.dist-info/top_level.txt
dv_mock_api-0.1.2.dist-info/RECORD
